previous year/2ndYear/sem4/cos/assignment/assignment2/Combinational Circuit Assignment/Demultiplexer_1to4.v
module demux1_4(in,sel,out);
input in;
input [1:0] sel;
output [3:0] out;


assign out = (sel == 2'b00) ? {in, 3'b000} :
             (sel == 2'b01) ? {3'b0, in, 2'b00} :
             (sel == 2'b10) ? {3'b00, in, 1'b0} :
             (sel == 2'b11) ? {3'b000, in} :
             4'b0000;
endmodule

previous year/2ndYear/sem4/cos/assignment/assignment2/Combinational Circuit Assignment/Demultiplexer_1to4_tb.v
`include "Demultiplexer_1to4.v"

module demultiplexer_1to4_tb();
    reg in;
    reg [1:0] sel;
    wire [3:0] out;

demux1_4 f1(in, sel, out);

initial begin
    $monitor("in=%b, sel=%b, out=%b\n", in, sel, out);
    #2 in = 1'b0; sel = 2'b00;
    #2 in = 1'b0; sel = 2'b01;
    #2 in = 1'b0; sel = 2'b10;
    #2 in = 1'b0; sel = 2'b11;
    #2 in = 1'b1; sel = 2'b00;
    #2 in = 1'b1; sel = 2'b01;
    #2 in = 1'b1; sel = 2'b10;
    #2 in = 1'b1; sel = 2'b11;
end
initial begin
    $dumpfile("out.vcd");
    $dumpvars;
    #50 $finish;
end

endmodule

previous year/2ndYear/sem4/cos/assignment/assignment2/Combinational Circuit Assignment/out.vcd
$date
	Wed Feb 28 22:35:18 2024
$end
$version
	Icarus Verilog
$end
$timescale
	1s
$end
$scope module demultiplexer_1to4_tb $end
$var wire 4 ! out [3:0] $end
$var reg 1 " in $end
$var reg 2 # sel [1:0] $end
$scope module f1 $end
$var wire 1 " in $end
$var wire 2 $ sel [1:0] $end
$var wire 4 % out [3:0] $end
$upscope $end
$upscope $end
$enddefinitions $end
#0
$dumpvars
bx %
bx $
bx #
x"
bx !
$end
#2
b0 !
b0 %
b0 #
b0 $
0"
#4
b1 #
b1 $
#6
b10 #
b10 $
#8
b11 #
b11 $
#10
b1000 !
b1000 %
b0 #
b0 $
1"
#12
b100 !
b100 %
b1 #
b1 $
#14
b10 !
b10 %
b10 #
b10 $
#16
b1 !
b1 %
b11 #
b11 $
